jusflaudio/__init__.py
jusflaudio/check_new_version.py
jusflaudio/fawhis.py
jusflaudio/mpvsa.py
jusflaudio/prepare_recode.py
jusflaudio/prepare_recode.sh
jusflaudio/shell_calls.py
jusflaudio/silero.py
jusflaudio/tool_checker.py
jusflaudio/whisper_wrapper.py
jusflaudio-0.2.18.dist-info/METADATA
jusflaudio-0.2.18.dist-info/WHEEL
jusflaudio-0.2.18.dist-info/entry_points.txt
jusflaudio-0.2.18.dist-info/RECORD
