Metadata-Version: 2.4
Name: jusflaudio
Version: 0.2.18
Summary: Useful audio tools
Requires-Python: >=3.10
Requires-Dist: argos-translate-files>=1.3.0
Requires-Dist: argostranslate>=1.9.6
Requires-Dist: autocorrect>=2.6.1
Requires-Dist: click>=8.2.1
Requires-Dist: console>=0.9911
Requires-Dist: faster-whisper>=1.1.1
Requires-Dist: pip>=25.3
Requires-Dist: pydub>=0.25.1
Requires-Dist: pysubs2>=1.8.0
Requires-Dist: requests>=2.32.4
Requires-Dist: silero-vad>=5.1.2
Requires-Dist: srt>=3.5.3
